[
    {
        "ep_type": "module_entry",
        "start_addr": "0x417910",
        "ep_args": [
            "0x4000",
            "0x4010",
            "0x4020",
            "0x4030"
        ],
        "apihash": "0528a4d35bc2f530ee3d2401f2723431a3e90abe4c12b834a33c7fb19c118e09",
        "apis": [
            {
                "pc": "0x417e18",
                "api_name": "api-ms-win-core-sysinfo-l1-1-0.GetSystemTimeAsFileTime",
                "args": [
                    "0x1211fd4"
                ],
                "ret_val": null
            },
            {
                "pc": "0x417e27",
                "api_name": "api-ms-win-core-processthreads-l1-1-0.GetCurrentProcessId",
                "args": [],
                "ret_val": "0x6e34"
            },
            {
                "pc": "0x417e30",
                "api_name": "api-ms-win-core-processthreads-l1-1-0.GetCurrentThreadId",
                "args": [],
                "ret_val": "0x6e48"
            },
            {
                "pc": "0x417e39",
                "api_name": "api-ms-win-core-sysinfo-l1-1-0.GetTickCount",
                "args": [],
                "ret_val": "0x5265c14"
            },
            {
                "pc": "0x417e4e",
                "api_name": "api-ms-win-core-profile-l1-1-0.QueryPerformanceCounter",
                "args": [
                    "0x1211fcc"
                ],
                "ret_val": "0x1"
            }
        ],
        "ret_val": "0x0",
        "error": {
            "type": "unsupported_api",
            "pc": "0xfeedf188",
            "address": "0xfeedf188",
            "instr": "disasm_failed",
            "regs": {
                "esp": "0x01211f88",
                "ebp": "0x01211f90",
                "eip": "0xfeedf188",
                "esi": "0x004012ec",
                "edi": "0x00417650",
                "eax": "0x00000000",
                "ebx": "0x00000000",
                "ecx": "0x00000100",
                "edx": "0x0000010b"
            },
            "stack": [
                "sp+0x00: 0x00417c55 -> emu.module.9db938cb9989a1882dbc0f344e510e76bafc4358b2aadb5dbb66a11d763a7ae6.0x400000",
                "sp+0x04: 0x00000000",
                "sp+0x08: 0x01211fa8 -> emu.stack.0x1200000",
                "sp+0x0c: 0x00417661 -> emu.module.9db938cb9989a1882dbc0f344e510e76bafc4358b2aadb5dbb66a11d763a7ae6.0x400000",
                "sp+0x10: 0x00000001",
                "sp+0x14: 0x00417891 -> emu.module.9db938cb9989a1882dbc0f344e510e76bafc4358b2aadb5dbb66a11d763a7ae6.0x400000",
                "sp+0x18: 0x00000000",
                "sp+0x1c: 0x00000001",
                "sp+0x20: 0x01211fe4 -> emu.stack.0x1200000",
                "sp+0x24: 0x0041776a -> emu.module.9db938cb9989a1882dbc0f344e510e76bafc4358b2aadb5dbb66a11d763a7ae6.0x400000",
                "sp+0x28: 0x004012e8 -> emu.module.9db938cb9989a1882dbc0f344e510e76bafc4358b2aadb5dbb66a11d763a7ae6.0x400000",
                "sp+0x2c: 0x004012f4 -> emu.module.9db938cb9989a1882dbc0f344e510e76bafc4358b2aadb5dbb66a11d763a7ae6.0x400000",
                "sp+0x30: 0xfe1af790",
                "sp+0x34: 0x00000000",
                "sp+0x38: 0x00000000",
                "sp+0x3c: 0x00000000"
            ],
            "api_name": "api-ms-win-core-libraryloader-l1-2-0.GetModuleHandleW"
        },
        "dynamic_code_segments": []
    }
]